prettypo/PrettyPageObject.py
prettypo/__init__.py
prettypo-0.0.5.dist-info/LICENSE
prettypo-0.0.5.dist-info/METADATA
prettypo-0.0.5.dist-info/WHEEL
prettypo-0.0.5.dist-info/top_level.txt
prettypo-0.0.5.dist-info/RECORD
