Metadata-Version: 2.1
Name: prettypo
Version: 0.0.5
Summary: Pretty Page Object Generator
Home-page: https://github.com/CoHuK/prettypo
Author: CoHuK
Author-email: prettypo@strongin.qa
License: UNKNOWN
Platform: UNKNOWN
Classifier: Programming Language :: Python :: 3
Classifier: License :: OSI Approved :: GNU General Public License v3 or later (GPLv3+)
Classifier: Operating System :: OS Independent
Requires-Python: >=3.4
Requires-Dist: selenium
